twitchrealtimehandler/__init__.py
twitchrealtimehandler/twitchgrabber.py
twitchrealtimehandler/twitchhandler.py
twitchrealtimehandler-0.1.2.dist-info/METADATA
twitchrealtimehandler-0.1.2.dist-info/WHEEL
twitchrealtimehandler-0.1.2.dist-info/RECORD
