Metadata-Version: 2.1
Name: twitchrealtimehandler
Version: 0.1.2
Summary: Package to handle real-time frames or audio segments from a twitch stream
Author: adrien.
Author-email: adrien.nouvellet@gmail.com
Requires-Python: >=3.9
Classifier: Programming Language :: Python :: 3
Classifier: Programming Language :: Python :: 3.9
Classifier: Programming Language :: Python :: 3.10
Classifier: Programming Language :: Python :: 3.11
Classifier: Programming Language :: Python :: 3.12
Requires-Dist: numpy (>=1.26.2,<2.0.0)
Requires-Dist: streamlink (>=6.4.2,<7.0.0)
